gh_fake_analyzer/__init__.py
gh_fake_analyzer/config.ini
gh_fake_analyzer/terminal.py
gh_fake_analyzer/modules/__init__.py
gh_fake_analyzer/modules/analyze.py
gh_fake_analyzer/modules/categorize_emails.py
gh_fake_analyzer/modules/fetch.py
gh_fake_analyzer/modules/filter.py
gh_fake_analyzer/modules/monitor.py
gh_fake_analyzer/modules/output.py
gh_fake_analyzer/target_list/ORGANIZATIONS
gh_fake_analyzer/target_list/USERNAMES
gh_fake_analyzer/tools/__init__.py
gh_fake_analyzer/tools/check_activity.py
gh_fake_analyzer/tools/dump_search_results.py
gh_fake_analyzer/tools/find_interesting_files.py
gh_fake_analyzer/tools/get_commit_author.py
gh_fake_analyzer/tools/get_external_prs.py
gh_fake_analyzer/tools/scan_organization.py
gh_fake_analyzer/tools/scan_repository.py
gh_fake_analyzer/utils/__init__.py
gh_fake_analyzer/utils/api.py
gh_fake_analyzer/utils/concurrent.py
gh_fake_analyzer/utils/config.py
gh_fake_analyzer/utils/data.py
gh_fake_analyzer/utils/github.py
gh_fake_analyzer-1.0.2.dist-info/METADATA
gh_fake_analyzer-1.0.2.dist-info/WHEEL
gh_fake_analyzer-1.0.2.dist-info/entry_points.txt
gh_fake_analyzer-1.0.2.dist-info/top_level.txt
gh_fake_analyzer-1.0.2.dist-info/RECORD
