Metadata-Version: 2.4
Name: gh-fake-analyzer
Version: 1.0.2
Summary: An OSINT utility for downloading, analyzing and detecting potential suspicious activity patterns in GitHub profiles
Home-page: https://github.com/shortdoom/gh-fake-analyzer
Author: blackbigswan
Author-email: blackbigswan@gmail.com
Classifier: Development Status :: 3 - Alpha
Classifier: Intended Audience :: Information Technology
Classifier: Intended Audience :: System Administrators
Classifier: Topic :: Security
Classifier: Topic :: Internet :: WWW/HTTP
Classifier: Topic :: Software Development :: Libraries :: Python Modules
Classifier: Topic :: Utilities
Classifier: Environment :: Console
Classifier: License :: OSI Approved :: MIT License
Classifier: Operating System :: OS Independent
Classifier: Programming Language :: Python :: 3
Classifier: Programming Language :: Python :: 3.7
Classifier: Programming Language :: Python :: 3.8
Classifier: Programming Language :: Python :: 3.9
Requires-Python: >=3.7
Requires-Dist: requests==2.32.3
Requires-Dist: requests-cache>=1.1.1
Requires-Dist: python-dotenv==1.0.1
Requires-Dist: python-dateutil==2.9.0.post0
Requires-Dist: GitPython==3.1.43
Requires-Dist: urllib3==2.2.2
Requires-Dist: aiohttp>=3.9.1
Dynamic: author
Dynamic: author-email
Dynamic: classifier
Dynamic: description
Dynamic: description-content-type
Dynamic: home-page
Dynamic: requires-dist
Dynamic: requires-python
Dynamic: summary
